{
  "league_id": "25044",
  "game_key": "357",
  "season": 2016,
  "teams": {
    "1": "Kempire Strikes Back",
    "2": "Bob Barker",
    "3": "Hold The Door",
    "4": "Thats Reddickulous",
    "5": "Bos Club",
    "6": "Pokey Reese's Pieces",
    "7": "cruzing to victory",
    "8": "Ålpha Bear #spicy ⚡⚡",
    "9": "#westcoastruth",
    "10": "Spirit of Troy",
    "11": "The Byung-HoLES",
    "12": "Gardy Goes Yardy",
    "13": "El Jefe",
    "14": "Eaton Dat Puss",
    "15": "New year NEW ME",
    "16": "TheKingOfTheNorth"
  },
  "season_totals": {},
  "team_season_stats": {
    "1": {
      "7": "783",
      "8": "1430",
      "12": "215",
      "13": "757",
      "16": "126",
      "21": "1153",
      "3": ".275",
      "4": ".346",
      "61": "510",
      "50": "1116.1",
      "28": "80",
      "29": "54",
      "39": "304",
      "42": "1183",
      "26": "3.85",
      "27": "1.17",
      "57": "9.54",
      "83": "79",
      "89": "96"
    },
    "2": {
      "7": "742",
      "8": "1394",
      "12": "184",
      "13": "659",
      "16": "128",
      "21": "1192",
      "3": ".268",
      "4": ".336",
      "61": "458",
      "50": "1196.0",
      "28": "72",
      "29": "59",
      "39": "352",
      "42": "1170",
      "26": "3.72",
      "27": "1.25",
      "57": "8.80",
      "83": "102",
      "89": "69"
    },
    "3": {
      "7": "717",
      "8": "1323",
      "12": "253",
      "13": "768",
      "16": "68",
      "21": "1240",
      "3": ".267",
      "4": ".328",
      "61": "537",
      "50": "1124.2",
      "28": "72",
      "29": "67",
      "39": "372",
      "42": "1095",
      "26": "3.67",
      "27": "1.23",
      "57": "8.76",
      "83": "91",
      "89": "70"
    },
    "4": {
      "7": "702",
      "8": "1334",
      "12": "184",
      "13": "672",
      "16": "84",
      "21": "1041",
      "3": ".269",
      "4": ".333",
      "61": "461",
      "50": "1067.1",
      "28": "67",
      "29": "58",
      "39": "352",
      "42": "973",
      "26": "3.88",
      "27": "1.33",
      "57": "8.20",
      "83": "82",
      "89": "87"
    },
    "5": {
      "7": "673",
      "8": "1332",
      "12": "183",
      "13": "673",
      "16": "92",
      "21": "1014",
      "3": ".264",
      "4": ".328",
      "61": "491",
      "50": "1256.1",
      "28": "85",
      "29": "64",
      "39": "331",
      "42": "1028",
      "26": "4.37",
      "27": "1.29",
      "57": "7.36",
      "83": "98",
      "89": "101"
    },
    "6": {
      "7": "658",
      "8": "1272",
      "12": "181",
      "13": "615",
      "16": "50",
      "21": "1072",
      "3": ".268",
      "4": ".328",
      "61": "451",
      "50": "1113.0",
      "28": "69",
      "29": "57",
      "39": "368",
      "42": "1093",
      "26": "3.84",
      "27": "1.24",
      "57": "8.84",
      "83": "75",
      "89": "117"
    },
    "7": {
      "7": "784",
      "8": "1408",
      "12": "230",
      "13": "767",
      "16": "78",
      "21": "1146",
      "3": ".272",
      "4": ".342",
      "61": "542",
      "50": "1205.1",
      "28": "83",
      "29": "56",
      "39": "364",
      "42": "1165",
      "26": "3.26",
      "27": "1.15",
      "57": "8.70",
      "83": "96",
      "89": "97"
    },
    "8": {
      "7": "792",
      "8": "1487",
      "12": "196",
      "13": "706",
      "16": "114",
      "21": "1009",
      "3": ".295",
      "4": ".365",
      "61": "536",
      "50": "1121.2",
      "28": "54",
      "29": "81",
      "39": "342",
      "42": "1138",
      "26": "3.67",
      "27": "1.21",
      "57": "9.13",
      "83": "88",
      "89": "98"
    },
    "9": {
      "7": "779",
      "8": "1403",
      "12": "184",
      "13": "696",
      "16": "111",
      "21": "1151",
      "3": ".274",
      "4": ".356",
      "61": "529",
      "50": "1350.2",
      "28": "86",
      "29": "79",
      "39": "413",
      "42": "1135",
      "26": "4.10",
      "27": "1.29",
      "57": "7.56",
      "83": "98",
      "89": "83"
    },
    "10": {
      "7": "736",
      "8": "1399",
      "12": "250",
      "13": "771",
      "16": "50",
      "21": "1098",
      "3": ".266",
      "4": ".335",
      "61": "527",
      "50": "925.2",
      "28": "63",
      "29": "45",
      "39": "260",
      "42": "913",
      "26": "3.39",
      "27": "1.11",
      "57": "8.88",
      "83": "81",
      "89": "76"
    },
    "11": {
      "7": "692",
      "8": "1258",
      "12": "233",
      "13": "716",
      "16": "65",
      "21": "1172",
      "3": ".262",
      "4": ".335",
      "61": "480",
      "50": "1197.2",
      "28": "79",
      "29": "71",
      "39": "347",
      "42": "1131",
      "26": "3.82",
      "27": "1.26",
      "57": "8.50",
      "83": "83",
      "89": "137"
    },
    "12": {
      "7": "761",
      "8": "1471",
      "12": "193",
      "13": "696",
      "16": "76",
      "21": "1075",
      "3": ".279",
      "4": ".342",
      "61": "519",
      "50": "1048.2",
      "28": "83",
      "29": "58",
      "39": "362",
      "42": "1055",
      "26": "3.42",
      "27": "1.23",
      "57": "9.05",
      "83": "81",
      "89": "74"
    },
    "13": {
      "7": "727",
      "8": "1415",
      "12": "221",
      "13": "791",
      "16": "44",
      "21": "1060",
      "3": ".277",
      "4": ".344",
      "61": "512",
      "50": "1243.2",
      "28": "73",
      "29": "74",
      "39": "402",
      "42": "1194",
      "26": "3.73",
      "27": "1.22",
      "57": "8.64",
      "83": "100",
      "89": "129"
    },
    "14": {
      "7": "434",
      "8": "816",
      "12": "99",
      "13": "350",
      "16": "50",
      "21": "837",
      "3": ".247",
      "4": ".314",
      "61": "279",
      "50": "867.2",
      "28": "50",
      "29": "52",
      "39": "307",
      "42": "896",
      "26": "3.91",
      "27": "1.30",
      "57": "9.29",
      "83": "56",
      "89": "114"
    },
    "15": {
      "7": "571",
      "8": "1173",
      "12": "174",
      "13": "644",
      "16": "65",
      "21": "949",
      "3": ".262",
      "4": ".321",
      "61": "407",
      "50": "905.0",
      "28": "48",
      "29": "54",
      "39": "319",
      "42": "876",
      "26": "4.31",
      "27": "1.38",
      "57": "8.71",
      "83": "61",
      "89": "76"
    },
    "16": {
      "7": "709",
      "8": "1323",
      "12": "182",
      "13": "678",
      "16": "83",
      "21": "1047",
      "3": ".270",
      "4": ".349",
      "61": "473",
      "50": "1318.1",
      "28": "83",
      "29": "97",
      "39": "432",
      "42": "1089",
      "26": "4.54",
      "27": "1.35",
      "57": "7.43",
      "83": "91",
      "89": "70"
    }
  },
  "weekly": {},
  "team_records_only": true
}
